gkm/__init__.py
gkm/amsgrad.py
gkm/gkm.py
gkm/glm.py
gkm/helpers.py
gkm/loss.py
gkm/newton.py
gkm/optimized_gkm.py
gkm/regularization.py
gkm/rendered.py
gkm/validation.py
gkm/deviance/__init__.py
gkm/deviance/base.py
gkm/deviance/binom.py
gkm/deviance/exponential.py
gkm/deviance/gaussian.py
gkm/deviance/negbinom.py
gkm/deviance/poisson.py
gkm/kernel/__init__.py
gkm/kernel/base.py
gkm/kernel/multi_rbf.py
gkm/kernel/multi_rbf_lazy.py
gkm/kernel/rbf.py
gkm/links/__init__.py
gkm/links/base.py
gkm/links/geometric.py
gkm/links/identity.py
gkm/links/log.py
gkm/links/logit.py
gkm-0.1.1.dist-info/LICENSE
gkm-0.1.1.dist-info/METADATA
gkm-0.1.1.dist-info/WHEEL
gkm-0.1.1.dist-info/top_level.txt
gkm-0.1.1.dist-info/RECORD
